gymix/__init__.py
gymix/client.py
gymix/exceptions.py
gymix/endpoints/__init__.py
gymix/endpoints/backup.py
gymix/endpoints/gym.py
gymix/endpoints/health.py
gymix/endpoints/users.py
gymix-1.0.2.dist-info/licenses/LICENSE
tests/__init__.py
tests/conftest.py
tests/test_client.py
gymix-1.0.2.dist-info/METADATA
gymix-1.0.2.dist-info/WHEEL
gymix-1.0.2.dist-info/top_level.txt
gymix-1.0.2.dist-info/RECORD
