Metadata-Version: 2.4
Name: gymix
Version: 1.0.2
Summary: Official Python SDK for Gymix API - Gym management and backup services
Home-page: https://github.com/mrssd/gymix-python-sdk
Author: Gymix Team
Author-email: Gymix Team <support@gymix.ir>
License: MIT
Project-URL: Homepage, https://gymix.ir
Project-URL: Documentation, https://docs.gymix.ir/python-sdk
Project-URL: Repository, https://github.com/mrssd/gymix-python-sdk
Project-URL: Bug Reports, https://github.com/mrssd/gymix-python-sdk/issues
Keywords: gymix,api,sdk,gym,management,backup
Classifier: Development Status :: 5 - Production/Stable
Classifier: Intended Audience :: Developers
Classifier: License :: OSI Approved :: MIT License
Classifier: Operating System :: OS Independent
Classifier: Programming Language :: Python :: 3
Classifier: Programming Language :: Python :: 3.7
Classifier: Programming Language :: Python :: 3.8
Classifier: Programming Language :: Python :: 3.9
Classifier: Programming Language :: Python :: 3.10
Classifier: Programming Language :: Python :: 3.11
Classifier: Programming Language :: Python :: 3.12
Classifier: Topic :: Software Development :: Libraries :: Python Modules
Classifier: Topic :: Internet :: WWW/HTTP :: Dynamic Content
Classifier: Topic :: Office/Business
Requires-Python: >=3.7
License-File: LICENSE
Requires-Dist: requests>=2.25.0
Requires-Dist: typing-extensions>=4.0.0; python_version < "3.8"
Provides-Extra: dev
Requires-Dist: pytest>=6.0; extra == "dev"
Requires-Dist: pytest-cov>=2.0; extra == "dev"
Requires-Dist: requests-mock>=1.9.0; extra == "dev"
Requires-Dist: black>=22.0; extra == "dev"
Requires-Dist: flake8>=4.0; extra == "dev"
Requires-Dist: mypy>=0.900; extra == "dev"
Requires-Dist: twine>=3.0; extra == "dev"
Dynamic: author
Dynamic: home-page
Dynamic: license-file
Dynamic: requires-python
